anymap_ts/__init__.py
anymap_ts/_version.py
anymap_ts/base.py
anymap_ts/basemaps.py
anymap_ts/cesium.py
anymap_ts/deckgl.py
anymap_ts/keplergl.py
anymap_ts/leaflet.py
anymap_ts/mapbox.py
anymap_ts/maplibre.py
anymap_ts/openlayers.py
anymap_ts/potree.py
anymap_ts/utils.py
anymap_ts/static/cesium.js
anymap_ts/static/deckgl.css
anymap_ts/static/deckgl.js
anymap_ts/static/leaflet.css
anymap_ts/static/leaflet.js
anymap_ts/static/mapbox.css
anymap_ts/static/mapbox.js
anymap_ts/static/maplibre.css
anymap_ts/static/maplibre.js
anymap_ts/static/openlayers.css
anymap_ts/static/openlayers.js
anymap_ts/templates/cesium.html
anymap_ts/templates/deckgl.html
anymap_ts/templates/keplergl.html
anymap_ts/templates/leaflet.html
anymap_ts/templates/mapbox.html
anymap_ts/templates/maplibre.html
anymap_ts/templates/openlayers.html
anymap_ts/templates/potree.html
anymap_ts-0.1.0.dist-info/METADATA
anymap_ts-0.1.0.dist-info/WHEEL
anymap_ts-0.1.0.dist-info/licenses/LICENSE
anymap_ts-0.1.0.dist-info/RECORD
