Metadata-Version: 2.4
Name: anymap-ts
Version: 0.1.0
Summary: A Python package for creating interactive maps with anywidget and TypeScript
Project-URL: Homepage, https://github.com/opengeos/anymap-ts
Project-URL: Documentation, https://anymap-ts.gishub.org
Project-URL: Repository, https://github.com/opengeos/anymap-ts
Project-URL: Issues, https://github.com/opengeos/anymap-ts/issues
Author-email: Qiusheng Wu <giswqs@gmail.com>
License-Expression: MIT
License-File: LICENSE
Keywords: anywidget,geospatial,gis,jupyter,maplibre,maps,typescript
Classifier: Development Status :: 4 - Beta
Classifier: Framework :: Jupyter
Classifier: Intended Audience :: Developers
Classifier: Intended Audience :: Science/Research
Classifier: License :: OSI Approved :: MIT License
Classifier: Operating System :: OS Independent
Classifier: Programming Language :: Python :: 3
Classifier: Programming Language :: Python :: 3.9
Classifier: Programming Language :: Python :: 3.10
Classifier: Programming Language :: Python :: 3.11
Classifier: Programming Language :: Python :: 3.12
Classifier: Topic :: Scientific/Engineering :: GIS
Requires-Python: >=3.9
Requires-Dist: anywidget>=0.9.0
Requires-Dist: traitlets>=5.0.0
Requires-Dist: xyzservices>=2023.10.0
Provides-Extra: all
Requires-Dist: geopandas>=0.14.0; extra == 'all'
Requires-Dist: localtileserver>=0.10.6; extra == 'all'
Requires-Dist: shapely>=2.0.0; extra == 'all'
Provides-Extra: dev
Requires-Dist: mypy>=1.8.0; extra == 'dev'
Requires-Dist: pre-commit>=3.6.0; extra == 'dev'
Requires-Dist: pytest-cov>=4.1.0; extra == 'dev'
Requires-Dist: pytest>=7.4.0; extra == 'dev'
Requires-Dist: ruff>=0.1.9; extra == 'dev'
Provides-Extra: docs
Requires-Dist: mkdocs-material>=9.5.0; extra == 'docs'
Requires-Dist: mkdocs>=1.5.0; extra == 'docs'
Requires-Dist: mkdocstrings[python]>=0.24.0; extra == 'docs'
Provides-Extra: raster
Requires-Dist: localtileserver>=0.10.6; extra == 'raster'
Provides-Extra: vector
Requires-Dist: geopandas>=0.14.0; extra == 'vector'
Requires-Dist: shapely>=2.0.0; extra == 'vector'
